{
  "data": [{
      "id": 101,
      "mainCon": {
        "name": "签证 · 护照"
      },
      "straList": [{
          "id": "319",
          "InfoLink": "护照"
        },
        {
          "id": "214",
          "InfoLink": "韩国签证"
        },
        {
          "id": "3164",
          "InfoLink": "中国公民免签入韩介绍"
        }
      ]
    },

    {
      "id": 102,
      "mainCon": {
        "name": "交通 · 出行"
      },
      "straList": [{
        "id": "1538",
        "InfoLink": "仁川机场"
      }, {
        "id": "1537",
        "InfoLink": "济州国际机场 "
      }, {
        "id": "3160",
        "InfoLink": "中国各大城市到首尔机票参考"
      }, {
        "id": "1543",
        "InfoLink": "韩国首尔地铁"
      }, {
        "id": "2897",
        "InfoLink": "韩国地铁失物找回方法"
      }, {
        "id": "1541",
        "InfoLink": "韩国首尔巴士"
      }, {
        "id": "1539",
        "InfoLink": "韩国KTX高速列车 "
      }, {
        "id": "1713",
        "InfoLink": "韩国机场大巴"
      }, {
        "id": "1540",
        "InfoLink": "韩国首尔出租车"
      }, {
        "id": "2891",
        "InfoLink": "韩国T-money交通卡"
      }, {
        "id": "3131",
        "InfoLink": "韩国机场铁路A’REX"
      }]
    },
    {
      "id": 103,
      "mainCon": {
        "name": "货币·退 税·保险"
      },
      "straList": [{
        "id": "=393",
        "InfoLink": "韩国退税制度"
      }, {
        "id": "=209",
        "InfoLink": "韩国货币"
      }, {
        "id": "=360",
        "InfoLink": "韩国购物银联卡使用介绍"
      }]
    },
    {
      "id": 104,
      "mainCon": {
        "name": "通信·应 急·须知"
      },
      "straList": [{
        "id": "=321",
        "InfoLink": "韩国通信指南"
      }, {
        "id": "=325",
        "InfoLink": "韩国邮政邮寄"
      }, {
        "id": "=323",
        "InfoLink": "韩国旅行信息咨询"
      }, {
        "id": "=322",
        "InfoLink": "韩国应急情况须知"
      }, {
        "id": "2897",
        "InfoLink": "韩国地铁失物找回方法"
      }, {
        "id": "=259",
        "InfoLink": "韩国的药"
      }, {
        "id": "=320",
        "InfoLink": "韩国气候、时差、电压等小贴士"
      }]
    }, {
      "id": 105,
      "mainCon": {
        "name": "预订·优惠"
      },
      "straList": [{
        "id": "otel",
        "InfoLink": "韩国酒店预订"
      }, {
        "id": "ndex",
        "InfoLink": "优惠券下载"
      }, {
        "id": "ndex",
        "InfoLink": "热门景点门票预订"
      }, {
        "id": "ndex",
        "InfoLink": "热门公演预订"
      }, {
        "id": "=226",
        "InfoLink": "WIFI预订"
      }, {
        "id": "ndex",
        "InfoLink": "火车票"
      }, {
        "id": "=122",
        "InfoLink": "一日游"
      }, {
        "id": "ndex",
        "InfoLink": "特惠"
      }]
    },
    {
      "id": 106,
      "mainCon": {
        "name": "民俗介绍"
      },
      "straList": [{
        "id": "d=75",
        "InfoLink": "韩国介绍"
      }, {
        "id": "=108",
        "InfoLink": "韩国节日"
      }, {
        "id": "pt:;",
        "InfoLink": "..."
      }, {
        "id": "pt:;",
        "InfoLink": ""
      }]
    },
    {
      "id": 107,
      "mainCon": {
        "name": "你知道吗"
      },
      "straList": [{
        "id": "3788",
        "InfoLink": "韩国旅游明智购物指南"
      }, {
        "id": "3499",
        "InfoLink": "明洞换钱所"
      }, {
        "id": "3411",
        "InfoLink": "韩服—韩国的传统之美"
      }, {
        "id": "3406",
        "InfoLink": "韩国旅游行李托运相关规定"
      }, {
        "id": "3391",
        "InfoLink": "韩国仁川机场大巴到江原道各地路线信息"
      }, {
        "id": "3388",
        "InfoLink": "韩国仁川机场大巴到庆尚道各地路线信息"
      }, {
        "id": "3387",
        "InfoLink": "韩国仁川机场大巴到全罗道各地路线信息"
      }, {
        "id": "3386",
        "InfoLink": "韩国仁川机场大巴到忠清道各地路线信息"
      }, {
        "id": "3385",
        "InfoLink": "韩国仁川机场大巴到京畿道各地路线信息"
      }, {
        "id": "3384",
        "InfoLink": "韩国仁川机场大巴到仁川各地路线信息"
      }]
    }, {
      "id": 108,
      "mainCon": {
        "name": "韩国地区介绍"
      },
      "straList": [{
        "id": "1528",
        "InfoLink": "首尔"
      }, {
        "id": "1529",
        "InfoLink": "釜山"
      }, {
        "id": "1530",
        "InfoLink": "济州"
      }, {
        "id": "1531",
        "InfoLink": "江原"
      }, {
        "id": "1536",
        "InfoLink": "仁川"
      }, {
        "id": "1532",
        "InfoLink": "京畿道"
      }, {
        "id": "1534",
        "InfoLink": "庆尚南道"
      }, {
        "id": "3421",
        "InfoLink": "庆尚北道"
      }, {
        "id": "1535",
        "InfoLink": "全罗南道"
      }, {
        "id": "3422",
        "InfoLink": "全罗北道"
      }, {
        "id": "1533",
        "InfoLink": "忠清南道"
      }, {
        "id": "3423",
        "InfoLink": "忠清北道"
      }, {
        "id": "3410",
        "InfoLink": "蔚山"
      }, {
        "id": "3409",
        "InfoLink": "大田"
      }]
    }
  ]
}